{"ongoing_trials": {}, "hyperparameters": {"space": [{"class_name": "Int", "config": {"name": "units", "default": null, "conditions": [], "min_value": 32, "max_value": 256, "step": 32, "sampling": "linear"}}, {"class_name": "Int", "config": {"name": "units_2", "default": null, "conditions": [], "min_value": 32, "max_value": 128, "step": 32, "sampling": "linear"}}, {"class_name": "Int", "config": {"name": "dense_units", "default": null, "conditions": [], "min_value": 16, "max_value": 64, "step": 16, "sampling": "linear"}}, {"class_name": "Float", "config": {"name": "learning_rate", "default": 0.0001, "conditions": [], "min_value": 0.0001, "max_value": 0.01, "step": null, "sampling": "log"}}], "values": {"units": 32, "units_2": 32, "dense_units": 16, "learning_rate": 0.0001}}, "start_order": ["00", "01", "02", "03", "04", "05", "06", "07", "08", "09"], "end_order": ["00", "01", "02", "03", "04", "05", "06", "07", "08", "09"], "run_times": {"00": 1, "01": 1, "02": 1, "03": 1, "04": 1, "05": 1, "06": 1, "07": 1, "08": 1, "09": 1}, "retry_queue": [], "seed": 7969, "seed_state": 8009, "tried_so_far": ["532c563545e1a4f75ad21f8eaa32244f", "51eb0e81d82bc1b92878de82eef94ed3", "69356be48b25934befe97ec4dc392a89", "17f1adcd615b09e05009121fd74f660f", "ddfdea9a78fa7920449c46cd0608cc99", "374db3c92c4a44c004d2d1c7b7ca57c5", "2b0c0c03131a1b77d9bd2cc993543b46", "da85f250a05c73c663ae7f38153e7a24", "0c0f5838558b91d4cbc88736ed95334e", "a15f2f67f59a446fc0008f4c23577e42"], "id_to_hash": {"00": "da85f250a05c73c663ae7f38153e7a24", "01": "374db3c92c4a44c004d2d1c7b7ca57c5", "02": "2b0c0c03131a1b77d9bd2cc993543b46", "03": "69356be48b25934befe97ec4dc392a89", "04": "51eb0e81d82bc1b92878de82eef94ed3", "05": "0c0f5838558b91d4cbc88736ed95334e", "06": "17f1adcd615b09e05009121fd74f660f", "07": "a15f2f67f59a446fc0008f4c23577e42", "08": "532c563545e1a4f75ad21f8eaa32244f", "09": "ddfdea9a78fa7920449c46cd0608cc99"}, "display": {"search_start": "2025-05-05T16:36:03.663327", "trial_start": {"00": "2025-05-05T16:36:03.663327", "01": "2025-05-05T16:37:54.431344", "02": "2025-05-05T16:39:50.604253", "03": "2025-05-05T16:41:34.423672", "04": "2025-05-05T16:43:37.305384", "05": "2025-05-05T16:44:16.054608", "06": "2025-05-05T16:46:39.999341", "07": "2025-05-05T16:48:23.319899", "08": "2025-05-05T16:49:41.805705", "09": "2025-05-05T16:50:52.683350"}, "trial_number": {"00": 1, "01": 2, "02": 3, "03": 4, "04": 5, "05": 6, "06": 7, "07": 8, "08": 9, "09": 10}}}